kilroy_face_discord/__init__.py
kilroy_face_discord/__main__.py
kilroy_face_discord/config.py
kilroy_face_discord/face.py
kilroy_face_discord/log.py
kilroy_face_discord/models.py
kilroy_face_discord/post.py
kilroy_face_discord/posters.py
kilroy_face_discord/processors.py
kilroy_face_discord/resources/__init__.py
kilroy_face_discord/resources/config.yaml
kilroy_face_discord/restrictions.py
kilroy_face_discord/scoring/__init__.py
kilroy_face_discord/scoring/modifiers.py
kilroy_face_discord/scoring/raw.py
kilroy_face_discord/scrapers.py
kilroy_face_discord-0.7.3.dist-info/entry_points.txt
kilroy_face_discord-0.7.3.dist-info/LICENSE
kilroy_face_discord-0.7.3.dist-info/WHEEL
kilroy_face_discord-0.7.3.dist-info/METADATA
kilroy_face_discord-0.7.3.dist-info/RECORD
