Metadata-Version: 2.1
Name: kilroy-face-discord
Version: 0.7.3
Summary: kilroy face for Discord 🎮
Home-page: https://github.com/kilroybot/kilroy-face-discord
Author: kilroy
Author-email: kilroymail@pm.me
Requires-Python: >=3.10,<3.11
Classifier: License :: OSI Approved :: MIT License
Classifier: Operating System :: OS Independent
Classifier: Programming Language :: Python :: 3
Classifier: Programming Language :: Python :: 3.10
Requires-Dist: detoxify (>=0.5,<0.6)
Requires-Dist: hikari (==2.0.0.dev109)
Requires-Dist: kilroy-face-server-py-sdk (>=0.9,<0.10)
Requires-Dist: numpy (>=1.23,<2.0)
Requires-Dist: omegaconf (>=2.2,<3.0)
Requires-Dist: platformdirs (>=2.5,<3.0)
Requires-Dist: pydantic[dotenv] (>=1.10,<2.0)
Requires-Dist: typer[all] (>=0.6,<0.7)
Project-URL: Documentation, https://kilroybot.github.io/kilroy-face-discord
Project-URL: Repository, https://github.com/kilroybot/kilroy-face-discord
